emojiswahili/__init__.py
emojiswahili/config.py
emojiswahili/core.py
emojiswahili/py.typed
emojiswahili/tokenizer.py
emojiswahili/unicode_codes/__init__.py
emojiswahili/unicode_codes/data_dict.py
emojiswahili/unicode_codes/emoji.json
emojiswahili-1.0.2.dist-info/LICENSE.txt
emojiswahili-1.0.2.dist-info/METADATA
emojiswahili-1.0.2.dist-info/WHEEL
emojiswahili-1.0.2.dist-info/top_level.txt
emojiswahili-1.0.2.dist-info/RECORD
