Metadata-Version: 2.2
Name: emojiswahili
Version: 1.0.2
Summary: Python library for working with emojis in Swahili
Author-email: eGARIDC <info@ega.go.tz>
Keywords: emoji,swahili,emojiswahili,python,unicode
Classifier: Development Status :: 5 - Production/Stable
Classifier: Intended Audience :: Developers
Classifier: Intended Audience :: Information Technology
Classifier: License :: OSI Approved :: BSD License
Classifier: Operating System :: OS Independent
Classifier: Programming Language :: Python :: 3
Classifier: Programming Language :: Python :: 3.7
Classifier: Programming Language :: Python :: 3.8
Classifier: Programming Language :: Python :: 3.9
Classifier: Programming Language :: Python :: 3.10
Classifier: Programming Language :: Python :: 3.11
Classifier: Programming Language :: Python :: 3.12
Classifier: Programming Language :: Python :: 3.13
Classifier: Programming Language :: Python :: Implementation :: CPython
Classifier: Programming Language :: Python :: Implementation :: PyPy
Classifier: Programming Language :: Python
Classifier: Topic :: Internet :: WWW/HTTP :: Dynamic Content
Classifier: Topic :: Multimedia :: Graphics :: Presentation
Classifier: Topic :: Software Development :: Libraries :: Python Modules
Classifier: Typing :: Typed
Requires-Python: >=3.7
License-File: LICENSE.txt
Requires-Dist: typing_extensions>=4.7.0; python_version < "3.9"
Provides-Extra: dev
Requires-Dist: pytest>=7.4.4; extra == "dev"
Requires-Dist: coverage; extra == "dev"
